Penalty_Kick_Saver/__init__.py
Penalty_Kick_Saver/penalty_kick_saver.py
Penalty_Kick_Saver-1.dist-info/LICENSE
Penalty_Kick_Saver-1.dist-info/METADATA
Penalty_Kick_Saver-1.dist-info/WHEEL
Penalty_Kick_Saver-1.dist-info/entry_points.txt
Penalty_Kick_Saver-1.dist-info/top_level.txt
Penalty_Kick_Saver-1.dist-info/RECORD
