Metadata-Version: 2.1
Name: Penalty-Kick-Saver
Version: 1
Summary: This is a simple game where the player becomes the goalkeeper whose job is to save the penalty kick.
Home-page: https://github.com/DtjiAppDev/PENALTY_KICK_SAVER
Author: Dtji AppDev
Author-email: dtjiappdev1999@gmail.com
License: MIT
Platform: UNKNOWN
Classifier: Programming Language :: Python :: 3
Classifier: Programming Language :: Python :: 3.7
